{
  "generatedAt": "2026-04-19T01:13:31.781Z",
  "allGreen": true,
  "summary": "All CI gates passing — E2E, Accessibility, Lighthouse.",
  "workflows": [
    {
      "name": "E2E Test Suite",
      "status": "success",
      "updatedAt": "2026-04-19T01:08:47Z"
    },
    {
      "name": "Accessibility Audit",
      "status": "success",
      "updatedAt": "2026-04-19T01:06:32Z"
    },
    {
      "name": "Lighthouse CI",
      "status": "success",
      "updatedAt": "2026-04-19T01:13:24Z"
    }
  ]
}
